{"name":"Sifteo Blicket Tutorial","tagline":"Science without soldering irons ","body":"#Sifteo Blickets\r\n\r\n##Introduction\r\nThis repo provides materials and instructions for creating Sifteo \"blickets\" to accompany our upcoming [blog post](http://).\r\n\r\n##What are blickets?\r\n\r\nDescribe Gopnik & Sobel (2000) Exp 1\r\n\r\n![][blicket_guts]\r\n![][blicket_detector]\r\n\r\n[blicket_guts]: http://depts.washington.edu/idl/images/blicket_internal_bottom.jpg\r\n[blicket_detector]: http://depts.washington.edu/idl/images/Blicket_top.jpg\r\n\r\n[Traditional blicket detector instructions](http://depts.washington.edu/idl/light_detail.htm)\r\n\r\n##What are Sifteo Blocks and how to they help?\r\nBrief description and links\r\n\r\n\r\n###Materials\r\n####Set 1: Four Identical Objects: \r\n![][green_rect]  ![][green_rect]  ![][green_rect] ![][green_rect]\r\n\r\n\r\n####Set 2: Same Color Different Shape:\r\n![][green_rect]  ![][green_sq]  ![][green_rounded_rect] ![][green_oval]\r\n\r\n####Set 3: Same Shape Different Color:\r\n![][red_rect]  ![][green_rect]  ![][yellow_rect] ![][blue_rect]\r\n\r\n####Set 4: Different Colors Different Shapes:\r\n![][green_sq]  ![][blue_oval]  ![][red_tri] ![][yellow_rounded_rect]\r\n\r\n####Set 5: Same Shape Conflicts Color:\r\n![][green_rounded_rect]  ![][green_rounded_rect]  ![][red_rounded_rect] ![][red_rounded_rect]\r\n\r\n####Set 6: Same Color Conflicts Shape:\r\n![][green_rounded_rect]  ![][green_rounded_rect]  ![][green_sq] ![][green_sq]\r\n\r\n####Set 7: Conflicts Shape and Color:\r\n![][red_rect]  ![][red_rect]  ![][green_sq] ![][green_sq]\r\n\r\n[green_rect]: https://github.com/jbmartin/SifteoBlickets/blob/master/assets/green_rect.png?raw=true\r\n[red_rect]: https://github.com/jbmartin/SifteoBlickets/blob/master/assets/red_rect.png?raw=true\r\n[yellow_rect]: https://github.com/jbmartin/SifteoBlickets/blob/master/assets/yellow_rect.png?raw=true\r\n[green_oval]: https://github.com/jbmartin/SifteoBlickets/blob/master/assets/green_oval.png?raw=true\r\n[green_sq]: https://github.com/jbmartin/SifteoBlickets/blob/master/assets/green_sq.png?raw=true\r\n[green_rounded_rect]: https://github.com/jbmartin/SifteoBlickets/blob/master/assets/green_rounded_rect.png?raw=true\r\n[blue_oval]: https://github.com/jbmartin/SifteoBlickets/blob/master/assets/blue_oval.png?raw=true\r\n[blue_rect]: https://github.com/jbmartin/SifteoBlickets/blob/master/assets/blue_rect.png?raw=true\r\n[red_tri]: https://github.com/jbmartin/SifteoBlickets/blob/master/assets/red_tri.png?raw=true\r\n[yellow_rounded_rect]: https://github.com/jbmartin/SifteoBlickets/blob/master/assets/yellow_rounded_rect.png?raw=true\r\n[red_rounded_rect]: https://github.com/jbmartin/SifteoBlickets/blob/master/assets/red_rounded_rect.png?raw=true\r\n\r\n###Procedure\r\n![][screen_shot]\r\n\r\n[screen_shot]: https://github.com/jbmartin/SifteoBlickets/blob/master/blog_assets/screen_shot.png?raw=true\r\n\r\n##Basics\r\n0. Preinstallation (check on dependencies e.g., clang, c++, etc.)\r\n1. Install the SDK from Sifteo\r\n  - [SDK](https://developers.sifteo.com/docs/SifteoSDK/0.9.8/getting_started.html)\r\n3. Clone this repo\r\n4. Run Siftulator (simulator)\r\n5. ...\r\n\r\n##Advanced\r\n1. Interventions (touch screen + neighborhoods)\r\n2. Continuous causal power (tilt)\r\n\r\n##Additional resources\r\n* [Getting Oriented with the Sifteo SDK](http://tech.sifteo.com/2013/01/08/getting-oriented-with-the-sifteo-sdk/)\r\n* [Getting Started: Basic Animation](http://tech.sifteo.com/2013/01/22/getting-started-basic-animation/)\r\n* [Neighborhoods and Locality](http://tech.sifteo.com/2013/01/03/neighborhoods-and-locality/)\r\n* [C++ basics](http://www.cprogramming.com/tutorial.html)\r\n","google":"","note":"Don't delete this file! It's used internally to help with page regeneration."}